setup.py
skywise_platform.egg-info/PKG-INFO
skywise_platform.egg-info/SOURCES.txt
skywise_platform.egg-info/dependency_links.txt
skywise_platform.egg-info/not-zip-safe
skywise_platform.egg-info/requires.txt
skywise_platform.egg-info/top_level.txt
skywiseplatform/__init__.py
skywiseplatform/datapoint.py
skywiseplatform/forecast.py
skywiseplatform/frame.py
skywiseplatform/product.py
skywiseplatform/style.py
skywiseplatform/tile.py