Metadata-Version: 1.1
Name: skywise-platform
Version: 0.1.7
Summary: SkyWise Platform API Python Client Library
Home-page: https://github.com/wdtinc/skywise-platform-py
Author: Weather Decision Technologies
Author-email: jstewart@wdtinc.com
License: UNKNOWN
Platform: UNKNOWN
Classifier: Development Status :: 3 - Alpha
Classifier: Intended Audience :: Developers
Classifier: Natural Language :: English
Classifier: Programming Language :: Python
Classifier: Programming Language :: Python :: 2.7
